stable_ethereum_rpc/__init__.py
stable_ethereum_rpc/config.py
stable_ethereum_rpc/web3_entity.py
stable_ethereum_rpc/web3_measure.py
stable_ethereum_rpc/stable_web3/__init__.py
stable_ethereum_rpc/stable_web3/available_mutiple_stable_web3.py
stable_ethereum_rpc/stable_web3/available_stable_web3.py
stable_ethereum_rpc/stable_web3/multiple_stable_web3.py
stable_ethereum_rpc/web3_list/__init__.py
stable_ethereum_rpc/web3_list/multiple_web3_list.py
stable_ethereum_rpc/web3_list/web3_list.py
stable_ethereum_rpc-0.0.5.dist-info/LICENSE
stable_ethereum_rpc-0.0.5.dist-info/METADATA
stable_ethereum_rpc-0.0.5.dist-info/WHEEL
stable_ethereum_rpc-0.0.5.dist-info/top_level.txt
stable_ethereum_rpc-0.0.5.dist-info/RECORD
