Metadata-Version: 2.1
Name: stable-ethereum-rpc
Version: 0.0.5
Summary: Stable Ethereum RPC
Home-page: https://github.com/phamhongphuc1999/stable-ethereum-rpc
Author: Phạm Hồng Phúc
Author-email: phamhongphuc12atm1@gmail.com
Project-URL: Bug Tracker, https://github.com/phamhongphuc1999/stable-ethereum-rpc
Classifier: Programming Language :: Python :: 3
Classifier: License :: OSI Approved :: MIT License
Classifier: Operating System :: OS Independent
Classifier: Environment :: Console
Requires-Python: >=3.6
License-File: LICENSE
Requires-Dist: web3 (==5.31.3)
Requires-Dist: timerit (==1.0.1)
Requires-Dist: APScheduler (==3.8.1)
Requires-Dist: tzlocal (==4.1)
